functional_pypelines/__init__.py
functional_pypelines/_immutables.py
functional_pypelines/_logging.py
functional_pypelines/_version.py
functional_pypelines/core.py
functional_pypelines/py.typed
functional_pypelines/types.py
functional_pypelines/validator.py
functional_pypelines/api/__init__.py
functional_pypelines/api/_import.py
functional_pypelines/api/cli.py
functional_pypelines/api/core.py
functional_pypelines-1.0.0.dist-info/METADATA
functional_pypelines-1.0.0.dist-info/WHEEL
functional_pypelines-1.0.0.dist-info/entry_points.txt
functional_pypelines-1.0.0.dist-info/licenses/LICENSE
functional_pypelines-1.0.0.dist-info/RECORD
