Metadata-Version: 2.3
Name: functional-pypelines
Version: 1.0.0
Summary: Framework for creating composable functions, including an API for running them via a JSON config.
Project-URL: repository, https://github.com/8451/functional-pypelines
Project-URL: documentation, https://8451.github.io/functional-pypelines
Project-URL: bugs, https://github.com/8451/functional-pypelines/issues
Author-email: Austin Warner <austin.warner@8451.com>, Michael Stoepel <michael.stoepel@8451.com>
License: MIT License
License-File: LICENSE
Classifier: Development Status :: 5 - Production/Stable
Classifier: License :: Other/Proprietary License
Classifier: Operating System :: MacOS
Classifier: Operating System :: Microsoft :: Windows
Classifier: Operating System :: POSIX :: Linux
Classifier: Programming Language :: Python
Classifier: Programming Language :: Python :: 3
Classifier: Programming Language :: Python :: 3.8
Classifier: Programming Language :: Python :: 3.9
Classifier: Programming Language :: Python :: 3.10
Classifier: Programming Language :: Python :: 3.11
Classifier: Programming Language :: Python :: 3.12
Requires-Python: >=3.8
Requires-Dist: click-default-group<2.0,>=1.2.2
Requires-Dist: click<9.0,>=7.0
Requires-Dist: typing-extensions>=4.0; python_version < '3.8'
Provides-Extra: dev
Requires-Dist: black; extra == 'dev'
Requires-Dist: bump2version; extra == 'dev'
Requires-Dist: coverage; extra == 'dev'
Requires-Dist: coverage-badge; extra == 'dev'
Requires-Dist: flake8>=3.7.9; extra == 'dev'
Requires-Dist: mypy; extra == 'dev'
Requires-Dist: myst-parser; extra == 'dev'
Requires-Dist: nbsphinx; extra == 'dev'
Requires-Dist: pre-commit; extra == 'dev'
Requires-Dist: pytest; extra == 'dev'
Requires-Dist: pytest-console-scripts; extra == 'dev'
Requires-Dist: pytest-cov; extra == 'dev'
Requires-Dist: recommonmark; extra == 'dev'
Requires-Dist: sphinx; extra == 'dev'
Requires-Dist: sphinx-rtd-theme; extra == 'dev'
Requires-Dist: sphinxcontrib-napoleon; extra == 'dev'
Requires-Dist: sphinxemoji; extra == 'dev'
Provides-Extra: doc
Requires-Dist: myst-parser; extra == 'doc'
Requires-Dist: nbsphinx; extra == 'doc'
Requires-Dist: recommonmark; extra == 'doc'
Requires-Dist: sphinx; extra == 'doc'
Requires-Dist: sphinx-rtd-theme; extra == 'doc'
Requires-Dist: sphinxcontrib-napoleon; extra == 'doc'
Requires-Dist: sphinxemoji; extra == 'doc'
Provides-Extra: test
Requires-Dist: coverage; extra == 'test'
Requires-Dist: coverage-badge; extra == 'test'
Requires-Dist: pytest; extra == 'test'
Requires-Dist: pytest-console-scripts; extra == 'test'
Requires-Dist: pytest-cov; extra == 'test'
